odoo/addons/helpdesk_ticket_document_pages/README.rst
odoo/addons/helpdesk_ticket_document_pages/__init__.py
odoo/addons/helpdesk_ticket_document_pages/__manifest__.py
odoo/addons/helpdesk_ticket_document_pages/i18n/ca_ES.po
odoo/addons/helpdesk_ticket_document_pages/i18n/es.po
odoo/addons/helpdesk_ticket_document_pages/models/__init__.py
odoo/addons/helpdesk_ticket_document_pages/models/document_page.py
odoo/addons/helpdesk_ticket_document_pages/models/helpdesk_ticket.py
odoo/addons/helpdesk_ticket_document_pages/static/description/document_page.png
odoo/addons/helpdesk_ticket_document_pages/static/description/icon.png
odoo/addons/helpdesk_ticket_document_pages/static/description/related_document_pages.png
odoo/addons/helpdesk_ticket_document_pages/static/description/ticket.png
odoo/addons/helpdesk_ticket_document_pages/tests/__init__.py
odoo/addons/helpdesk_ticket_document_pages/tests/test_helpdesk_ticket.py
odoo/addons/helpdesk_ticket_document_pages/views/document_page.xml
odoo/addons/helpdesk_ticket_document_pages/views/helpdesk_ticket.xml
odoo12_addon_helpdesk_ticket_document_pages-12.0.2.0.1.dist-info/METADATA
odoo12_addon_helpdesk_ticket_document_pages-12.0.2.0.1.dist-info/WHEEL
odoo12_addon_helpdesk_ticket_document_pages-12.0.2.0.1.dist-info/top_level.txt
odoo12_addon_helpdesk_ticket_document_pages-12.0.2.0.1.dist-info/RECORD
