Metadata-Version: 2.1
Name: odoo12-addon-helpdesk-ticket-document-pages
Version: 12.0.2.0.1
Summary: ODOO module to relate helpdesk tickets with knowledge document pages.
Home-page: https://gitlab.com/somitcoop/erp-research/odoo-helpdesk
Author: Som It Cooperatiu SCCL, Som Connexió SCCL, Odoo Community Association (OCA)",
Author-email: support@odoo-community.org
License: AGPL-3
Platform: UNKNOWN
Classifier: Programming Language :: Python
Classifier: Framework :: Odoo
Classifier: Framework :: Odoo :: 12.0
Classifier: License :: OSI Approved :: GNU Affero General Public License v3
Requires-Python: >=3.5
Requires-Dist: odoo12-addon-document-page
Requires-Dist: odoo12-addon-document-page-tag
Requires-Dist: odoo12-addon-helpdesk-mgmt
Requires-Dist: odoo (<12.1dev,>=12.0a)
